Metadata-Version: 2.1
Name: gpged
Version: 0.0.4
Summary: GUI for encrypting and decrypting text with GPG.
Author-email: Sky Moore <i@msky.me>
License: Copyright 2022 Sky Moore
Keywords: gpg,gnupg,pgp,gui,encryption,decryption,cryptography
Classifier: Intended Audience :: Developers
Classifier: Natural Language :: English
Classifier: Programming Language :: Python :: 3.10
License-File: LICENSE
